moabdb/__init__.py
moabdb/constants.py
moabdb/core.py
moabdb/errors.py
moabdb/get_equity.py
moabdb/lib.py
moabdb/proto_wrapper.py
moabdb/protocol_pb2.py
moabdb/timewindows.py
moabdb-0.1.55.dist-info/LICENSE
moabdb-0.1.55.dist-info/WHEEL
moabdb-0.1.55.dist-info/METADATA
moabdb-0.1.55.dist-info/RECORD
