Metadata-Version: 2.1
Name: moabdb
Version: 0.1.55
Summary: MoabDB
Author-email: Jackson Coxson <jkcoxson@gmail.com>, Brian Roseman <brian@roseman.dev>
Classifier: License :: OSI Approved :: MIT License
Requires-Dist: pandas
Requires-Dist: protobuf
Requires-Dist: requests
Requires-Dist: pyarrow
Project-URL: Home, https://moabdb.com
Project-URL: Source, https://github.com/MoabDB/moabdb-py
